{
  "structs": [
    {
      "name": "MaskedBankAccount",
      "visibility": "pub",
      "fields": [],
      "derives": [
        "Clone",
        "Debug",
        "Eq",
        "PartialEq",
        "serde::Serialize",
        "serde::Deserialize"
      ],
      "line": 34
    },
    {
      "name": "Request",
      "visibility": "pub",
      "fields": [
        "url",
        "headers",
        "method",
        "certificate",
        "certificate_key",
        "body",
        "ca_certificate"
      ],
      "derives": [
        "Debug",
        "thiserror::Error",
        "Clone",
        "Copy",
        "Debug",
        "Eq",
        "PartialEq",
        "Deserialize",
        "Serialize",
        "strum::Display",
        "strum::EnumString",
        "ToSchema",
        "Deserialize",
        "Serialize",
        "Debug",
        "Debug"
      ],
      "line": 52
    },
    {
      "name": "MultipartData",
      "visibility": "pub",
      "fields": [
        "parts"
      ],
      "derives": [
        "Debug",
        "thiserror::Error",
        "Clone",
        "Copy",
        "Debug",
        "Eq",
        "PartialEq",
        "Deserialize",
        "Serialize",
        "strum::Display",
        "strum::EnumString",
        "ToSchema",
        "Deserialize",
        "Serialize",
        "Debug",
        "Debug",
        "Serialize",
        "Debug",
        "Clone",
        "Serialize"
      ],
      "line": 83
    },
    {
      "name": "RequestBuilder",
      "visibility": "pub",
      "fields": [
        "url",
        "headers",
        "method",
        "certificate",
        "certificate_key",
        "body",
        "ca_certificate"
      ],
      "derives": [
        "Debug",
        "thiserror::Error",
        "Clone",
        "Copy",
        "Debug",
        "Eq",
        "PartialEq",
        "Deserialize",
        "Serialize",
        "strum::Display",
        "strum::EnumString",
        "ToSchema",
        "Deserialize",
        "Serialize",
        "Debug",
        "Debug",
        "Serialize",
        "Debug",
        "Clone",
        "Serialize",
        "Debug",
        "Clone",
        "Serialize",
        "Debug"
      ],
      "line": 249
    },
    {
      "name": "StringMinorUnitForConnector",
      "visibility": "pub",
      "fields": [],
      "derives": [
        "Default",
        "Debug",
        "Clone",
        "Copy",
        "PartialEq"
      ],
      "line": 45
    },
    {
      "name": "StringMajorUnitForCore",
      "visibility": "pub",
      "fields": [],
      "derives": [
        "Default",
        "Debug",
        "Clone",
        "Copy",
        "PartialEq",
        "Default",
        "Debug",
        "serde::Deserialize",
        "serde::Serialize",
        "Clone",
        "Copy",
        "PartialEq"
      ],
      "line": 68
    },
    {
      "name": "StringMajorUnitForConnector",
      "visibility": "pub",
      "fields": [],
      "derives": [
        "Default",
        "Debug",
        "Clone",
        "Copy",
        "PartialEq",
        "Default",
        "Debug",
        "serde::Deserialize",
        "serde::Serialize",
        "Clone",
        "Copy",
        "PartialEq",
        "Default",
        "Debug",
        "serde::Deserialize",
        "serde::Serialize",
        "Clone",
        "Copy",
        "PartialEq"
      ],
      "line": 90
    },
    {
      "name": "FloatMajorUnitForConnector",
      "visibility": "pub",
      "fields": [],
      "derives": [
        "Default",
        "Debug",
        "Clone",
        "Copy",
        "PartialEq",
        "Default",
        "Debug",
        "serde::Deserialize",
        "serde::Serialize",
        "Clone",
        "Copy",
        "PartialEq",
        "Default",
        "Debug",
        "serde::Deserialize",
        "serde::Serialize",
        "Clone",
        "Copy",
        "PartialEq",
        "Default",
        "Debug",
        "serde::Deserialize",
        "serde::Serialize",
        "Clone",
        "Copy",
        "PartialEq"
      ],
      "line": 113
    },
    {
      "name": "MinorUnitForConnector",
      "visibility": "pub",
      "fields": [],
      "derives": [
        "Default",
        "Debug",
        "Clone",
        "Copy",
        "PartialEq",
        "Default",
        "Debug",
        "serde::Deserialize",
        "serde::Serialize",
        "Clone",
        "Copy",
        "PartialEq",
        "Default",
        "Debug",
        "serde::Deserialize",
        "serde::Serialize",
        "Clone",
        "Copy",
        "PartialEq",
        "Default",
        "Debug",
        "serde::Deserialize",
        "serde::Serialize",
        "Clone",
        "Copy",
        "PartialEq",
        "Default",
        "Debug",
        "serde::Deserialize",
        "serde::Serialize",
        "Clone",
        "Copy",
        "PartialEq"
      ],
      "line": 135
    },
    {
      "name": "MinorUnit",
      "visibility": "pub",
      "fields": [],
      "derives": [
        "Default",
        "Debug",
        "Clone",
        "Copy",
        "PartialEq",
        "Default",
        "Debug",
        "serde::Deserialize",
        "serde::Serialize",
        "Clone",
        "Copy",
        "PartialEq",
        "Default",
        "Debug",
        "serde::Deserialize",
        "serde::Serialize",
        "Clone",
        "Copy",
        "PartialEq",
        "Default",
        "Debug",
        "serde::Deserialize",
        "serde::Serialize",
        "Clone",
        "Copy",
        "PartialEq",
        "Default",
        "Debug",
        "serde::Deserialize",
        "serde::Serialize",
        "Clone",
        "Copy",
        "PartialEq",
        "Default",
        "Debug",
        "serde::Deserialize",
        "serde::Serialize",
        "Clone",
        "Copy",
        "PartialEq",
        "Eq",
        "Hash",
        "ToSchema",
        "PartialOrd"
      ],
      "line": 170
    },
    {
      "name": "StringMinorUnit",
      "visibility": "pub",
      "fields": [],
      "derives": [
        "Default",
        "Debug",
        "Clone",
        "Copy",
        "PartialEq",
        "Default",
        "Debug",
        "serde::Deserialize",
        "serde::Serialize",
        "Clone",
        "Copy",
        "PartialEq",
        "Default",
        "Debug",
        "serde::Deserialize",
        "serde::Serialize",
        "Clone",
        "Copy",
        "PartialEq",
        "Default",
        "Debug",
        "serde::Deserialize",
        "serde::Serialize",
        "Clone",
        "Copy",
        "PartialEq",
        "Default",
        "Debug",
        "serde::Deserialize",
        "serde::Serialize",
        "Clone",
        "Copy",
        "PartialEq",
        "Default",
        "Debug",
        "serde::Deserialize",
        "serde::Serialize",
        "Clone",
        "Copy",
        "PartialEq",
        "Eq",
        "Hash",
        "ToSchema",
        "PartialOrd",
        "Default",
        "Debug",
        "serde::Deserialize",
        "serde::Serialize",
        "Clone",
        "PartialEq",
        "Eq",
        "Hash",
        "ToSchema",
        "PartialOrd"
      ],
      "line": 305
    },
    {
      "name": "FloatMajorUnit",
      "visibility": "pub",
      "fields": [],
      "derives": [
        "Default",
        "Debug",
        "Clone",
        "Copy",
        "PartialEq",
        "Default",
        "Debug",
        "serde::Deserialize",
        "serde::Serialize",
        "Clone",
        "Copy",
        "PartialEq",
        "Default",
        "Debug",
        "serde::Deserialize",
        "serde::Serialize",
        "Clone",
        "Copy",
        "PartialEq",
        "Default",
        "Debug",
        "serde::Deserialize",
        "serde::Serialize",
        "Clone",
        "Copy",
        "PartialEq",
        "Default",
        "Debug",
        "serde::Deserialize",
        "serde::Serialize",
        "Clone",
        "Copy",
        "PartialEq",
        "Default",
        "Debug",
        "serde::Deserialize",
        "serde::Serialize",
        "Clone",
        "Copy",
        "PartialEq",
        "Eq",
        "Hash",
        "ToSchema",
        "PartialOrd",
        "Default",
        "Debug",
        "serde::Deserialize",
        "serde::Serialize",
        "Clone",
        "PartialEq",
        "Eq",
        "Hash",
        "ToSchema",
        "PartialOrd",
        "Default",
        "Debug",
        "serde::Deserialize",
        "serde::Serialize",
        "Clone",
        "Copy",
        "PartialEq"
      ],
      "line": 336
    },
    {
      "name": "StringMajorUnit",
      "visibility": "pub",
      "fields": [],
      "derives": [
        "Default",
        "Debug",
        "Clone",
        "Copy",
        "PartialEq",
        "Default",
        "Debug",
        "serde::Deserialize",
        "serde::Serialize",
        "Clone",
        "Copy",
        "PartialEq",
        "Default",
        "Debug",
        "serde::Deserialize",
        "serde::Serialize",
        "Clone",
        "Copy",
        "PartialEq",
        "Default",
        "Debug",
        "serde::Deserialize",
        "serde::Serialize",
        "Clone",
        "Copy",
        "PartialEq",
        "Default",
        "Debug",
        "serde::Deserialize",
        "serde::Serialize",
        "Clone",
        "Copy",
        "PartialEq",
        "Default",
        "Debug",
        "serde::Deserialize",
        "serde::Serialize",
        "Clone",
        "Copy",
        "PartialEq",
        "Eq",
        "Hash",
        "ToSchema",
        "PartialOrd",
        "Default",
        "Debug",
        "serde::Deserialize",
        "serde::Serialize",
        "Clone",
        "PartialEq",
        "Eq",
        "Hash",
        "ToSchema",
        "PartialOrd",
        "Default",
        "Debug",
        "serde::Deserialize",
        "serde::Serialize",
        "Clone",
        "Copy",
        "PartialEq",
        "Default",
        "Debug",
        "serde::Deserialize",
        "serde::Serialize",
        "Clone",
        "PartialEq",
        "Eq"
      ],
      "line": 374
    },
    {
      "name": "Money",
      "visibility": "pub",
      "fields": [
        "amount",
        "currency"
      ],
      "derives": [
        "Default",
        "Debug",
        "Clone",
        "Copy",
        "PartialEq",
        "Default",
        "Debug",
        "serde::Deserialize",
        "serde::Serialize",
        "Clone",
        "Copy",
        "PartialEq",
        "Default",
        "Debug",
        "serde::Deserialize",
        "serde::Serialize",
        "Clone",
        "Copy",
        "PartialEq",
        "Default",
        "Debug",
        "serde::Deserialize",
        "serde::Serialize",
        "Clone",
        "Copy",
        "PartialEq",
        "Default",
        "Debug",
        "serde::Deserialize",
        "serde::Serialize",
        "Clone",
        "Copy",
        "PartialEq",
        "Default",
        "Debug",
        "serde::Deserialize",
        "serde::Serialize",
        "Clone",
        "Copy",
        "PartialEq",
        "Eq",
        "Hash",
        "ToSchema",
        "PartialOrd",
        "Default",
        "Debug",
        "serde::Deserialize",
        "serde::Serialize",
        "Clone",
        "PartialEq",
        "Eq",
        "Hash",
        "ToSchema",
        "PartialOrd",
        "Default",
        "Debug",
        "serde::Deserialize",
        "serde::Serialize",
        "Clone",
        "Copy",
        "PartialEq",
        "Default",
        "Debug",
        "serde::Deserialize",
        "serde::Serialize",
        "Clone",
        "PartialEq",
        "Eq",
        "Default",
        "Debug",
        "serde::Deserialize",
        "serde::Serialize",
        "Clone",
        "PartialEq",
        "Eq",
        "Hash",
        "ToSchema"
      ],
      "line": 419
    },
    {
      "name": "TimeRange",
      "visibility": "pub",
      "fields": [
        "start_time",
        "end_time"
      ],
      "derives": [
        "Default",
        "Debug",
        "Clone",
        "Copy",
        "PartialEq",
        "Default",
        "Debug",
        "serde::Deserialize",
        "serde::Serialize",
        "Clone",
        "Copy",
        "PartialEq",
        "Default",
        "Debug",
        "serde::Deserialize",
        "serde::Serialize",
        "Clone",
        "Copy",
        "PartialEq",
        "Default",
        "Debug",
        "serde::Deserialize",
        "serde::Serialize",
        "Clone",
        "Copy",
        "PartialEq",
        "Default",
        "Debug",
        "serde::Deserialize",
        "serde::Serialize",
        "Clone",
        "Copy",
        "PartialEq",
        "Default",
        "Debug",
        "serde::Deserialize",
        "serde::Serialize",
        "Clone",
        "Copy",
        "PartialEq",
        "Eq",
        "Hash",
        "ToSchema",
        "PartialOrd",
        "Default",
        "Debug",
        "serde::Deserialize",
        "serde::Serialize",
        "Clone",
        "PartialEq",
        "Eq",
        "Hash",
        "ToSchema",
        "PartialOrd",
        "Default",
        "Debug",
        "serde::Deserialize",
        "serde::Serialize",
        "Clone",
        "Copy",
        "PartialEq",
        "Default",
        "Debug",
        "serde::Deserialize",
        "serde::Serialize",
        "Clone",
        "PartialEq",
        "Eq",
        "Default",
        "Debug",
        "serde::Deserialize",
        "serde::Serialize",
        "Clone",
        "PartialEq",
        "Eq",
        "Hash",
        "ToSchema",
        "Debug",
        "Clone",
        "Copy",
        "serde::Serialize",
        "serde::Deserialize",
        "PartialEq",
        "Eq",
        "Hash",
        "ToSchema"
      ],
      "line": 428
    },
    {
      "name": "SemanticVersion",
      "visibility": "pub",
      "fields": [],
      "derives": [
        "Default",
        "Debug",
        "Clone",
        "Copy",
        "PartialEq",
        "Default",
        "Debug",
        "serde::Deserialize",
        "serde::Serialize",
        "Clone",
        "Copy",
        "PartialEq",
        "Default",
        "Debug",
        "serde::Deserialize",
        "serde::Serialize",
        "Clone",
        "Copy",
        "PartialEq",
        "Default",
        "Debug",
        "serde::Deserialize",
        "serde::Serialize",
        "Clone",
        "Copy",
        "PartialEq",
        "Default",
        "Debug",
        "serde::Deserialize",
        "serde::Serialize",
        "Clone",
        "Copy",
        "PartialEq",
        "Default",
        "Debug",
        "serde::Deserialize",
        "serde::Serialize",
        "Clone",
        "Copy",
        "PartialEq",
        "Eq",
        "Hash",
        "ToSchema",
        "PartialOrd",
        "Default",
        "Debug",
        "serde::Deserialize",
        "serde::Serialize",
        "Clone",
        "PartialEq",
        "Eq",
        "Hash",
        "ToSchema",
        "PartialOrd",
        "Default",
        "Debug",
        "serde::Deserialize",
        "serde::Serialize",
        "Clone",
        "Copy",
        "PartialEq",
        "Default",
        "Debug",
        "serde::Deserialize",
        "serde::Serialize",
        "Clone",
        "PartialEq",
        "Eq",
        "Default",
        "Debug",
        "serde::Deserialize",
        "serde::Serialize",
        "Clone",
        "PartialEq",
        "Eq",
        "Hash",
        "ToSchema",
        "Debug",
        "Clone",
        "Copy",
        "serde::Serialize",
        "serde::Deserialize",
        "PartialEq",
        "Eq",
        "Hash",
        "ToSchema",
        "Debug",
        "Clone",
        "PartialEq",
        "Eq",
        "Ord",
        "PartialOrd",
        "Serialize",
        "serde::Deserialize"
      ],
      "line": 441
    },
    {
      "name": "MaskedSerdeValue",
      "visibility": "pub",
      "fields": [
        "inner"
      ],
      "derives": [
        "Debug",
        "Clone",
        "Serialize"
      ],
      "line": 20
    },
    {
      "name": "Event",
      "visibility": "pub",
      "fields": [
        "request_id",
        "timestamp",
        "flow_type",
        "connector",
        "url",
        "stage",
        "latency_ms",
        "status_code",
        "request_data",
        "response_data",
        "headers",
        "additional_fields",
        "lineage_ids"
      ],
      "derives": [
        "Debug",
        "Clone",
        "Serialize",
        "Clone",
        "Debug",
        "Eq",
        "PartialEq",
        "Serialize",
        "Debug",
        "Clone",
        "Serialize"
      ],
      "line": 214
    },
    {
      "name": "EventConfig",
      "visibility": "pub",
      "fields": [
        "enabled",
        "topic",
        "brokers",
        "partition_key_field",
        "transformations",
        "static_values",
        "extractions"
      ],
      "derives": [
        "Debug",
        "Clone",
        "Serialize",
        "Clone",
        "Debug",
        "Eq",
        "PartialEq",
        "Serialize",
        "Debug",
        "Clone",
        "Serialize",
        "strum::Display",
        "Debug",
        "Clone",
        "Copy",
        "PartialEq",
        "Eq",
        "Serialize",
        "Deserialize",
        "Debug",
        "Clone",
        "Serialize",
        "Deserialize",
        "Debug",
        "Clone",
        "Deserialize",
        "Serialize",
        "PartialEq",
        "config_patch_derive::Patch"
      ],
      "line": 394
    },
    {
      "name": "HeaderMaskingConfig",
      "visibility": "pub",
      "fields": [
        "unmasked_keys"
      ],
      "derives": [
        "Debug",
        "Clone",
        "PartialEq",
        "Eq"
      ],
      "line": 11
    },
    {
      "name": "Config",
      "visibility": "",
      "fields": [
        "keys"
      ],
      "derives": [
        "serde::Deserialize"
      ],
      "line": 43
    },
    {
      "name": "HeaderMaskingConfigPatch",
      "visibility": "pub",
      "fields": [
        "keys"
      ],
      "derives": [
        "Debug",
        "Clone",
        "PartialEq",
        "Eq",
        "Debug",
        "Default",
        "Deserialize",
        "Serialize"
      ],
      "line": 70
    },
    {
      "name": "MaskedMetadata",
      "visibility": "pub",
      "fields": [
        "raw_metadata",
        "masking_config"
      ],
      "derives": [
        "Debug",
        "Clone",
        "PartialEq",
        "Eq",
        "Debug",
        "Default",
        "Deserialize",
        "Serialize",
        "Clone"
      ],
      "line": 96
    },
    {
      "name": "DDMMYYYY",
      "visibility": "pub",
      "fields": [],
      "derives": [
        "Debug",
        "Debug",
        "Clone"
      ],
      "line": 149
    },
    {
      "name": "YYYYMMDD",
      "visibility": "pub",
      "fields": [],
      "derives": [
        "Debug",
        "Debug",
        "Clone",
        "Debug",
        "Clone"
      ],
      "line": 152
    },
    {
      "name": "YYYYMMDDHHmmss",
      "visibility": "pub",
      "fields": [],
      "derives": [
        "Debug",
        "Debug",
        "Clone",
        "Debug",
        "Clone",
        "Debug",
        "Clone"
      ],
      "line": 155
    },
    {
      "name": "DateTime",
      "visibility": "pub",
      "fields": [
        "inner",
        "value"
      ],
      "derives": [
        "Debug",
        "Debug",
        "Clone",
        "Debug",
        "Clone",
        "Debug",
        "Clone",
        "Debug",
        "Deserialize",
        "Clone"
      ],
      "line": 159
    },
    {
      "name": "GlobalId",
      "visibility": "pub(crate)",
      "fields": [],
      "derives": [
        "Debug",
        "Clone",
        "Hash",
        "PartialEq",
        "Eq",
        "serde::Serialize"
      ],
      "line": 20
    },
    {
      "name": "CellId",
      "visibility": "pub",
      "fields": [],
      "derives": [
        "Debug",
        "Clone",
        "Hash",
        "PartialEq",
        "Eq",
        "serde::Serialize",
        "Clone",
        "Copy",
        "Debug",
        "Clone",
        "Hash",
        "PartialEq",
        "Eq"
      ],
      "line": 51
    },
    {
      "name": "SuperpositionConfig",
      "visibility": "pub",
      "fields": [
        "config"
      ],
      "derives": [
        "Debug",
        "thiserror::Error",
        "Debug",
        "Clone"
      ],
      "line": 36
    },
    {
      "name": "ConnectorUrls",
      "visibility": "pub",
      "fields": [
        "base_url",
        "dispute_base_url",
        "secondary_base_url",
        "third_base_url",
        "base_url_bank_redirects"
      ],
      "derives": [
        "Debug",
        "thiserror::Error",
        "Debug",
        "Clone",
        "Debug",
        "Clone",
        "Default"
      ],
      "line": 141
    },
    {
      "name": "Email",
      "visibility": "pub",
      "fields": [],
      "derives": [
        "Debug",
        "Copy",
        "Clone",
        "Deserialize",
        "serde::Serialize",
        "serde::Deserialize",
        "Debug",
        "Clone",
        "PartialEq",
        "Eq",
        "Default"
      ],
      "line": 37
    },
    {
      "name": "IntegrityCheckError",
      "visibility": "pub",
      "fields": [
        "field_names",
        "connector_transaction_id"
      ],
      "derives": [
        "Debug",
        "thiserror::Error",
        "Debug",
        "thiserror::Error",
        "Clone",
        "PartialEq",
        "Debug",
        "Clone",
        "thiserror::Error",
        "PartialEq",
        "Debug",
        "thiserror::Error",
        "Debug",
        "Clone",
        "PartialEq",
        "Default"
      ],
      "line": 174
    },
    {
      "name": "LineageIds",
      "visibility": "pub",
      "fields": [
        "prefix",
        "inner"
      ],
      "derives": [
        "Debug",
        "Clone",
        "PartialEq",
        "Eq",
        "Default"
      ],
      "line": 9
    },
    {
      "name": "AlphaNumericId",
      "visibility": "pub(crate)",
      "fields": [],
      "derives": [
        "Debug",
        "PartialEq",
        "Hash",
        "Serialize",
        "Clone",
        "Eq"
      ],
      "line": 15
    },
    {
      "name": "AlphaNumericIdError",
      "visibility": "pub",
      "fields": [],
      "derives": [
        "Debug",
        "PartialEq",
        "Hash",
        "Serialize",
        "Clone",
        "Eq",
        "Debug",
        "Deserialize",
        "Hash",
        "Serialize",
        "Error",
        "Eq",
        "PartialEq"
      ],
      "line": 27
    },
    {
      "name": "CustomerId",
      "visibility": "pub",
      "fields": [],
      "derives": [
        "Debug",
        "PartialEq",
        "Hash",
        "Serialize",
        "Clone",
        "Eq",
        "Debug",
        "Deserialize",
        "Hash",
        "Serialize",
        "Error",
        "Eq",
        "PartialEq",
        "Debug",
        "Clone",
        "Serialize",
        "Hash",
        "PartialEq",
        "Eq"
      ],
      "line": 54
    },
    {
      "name": "MerchantId",
      "visibility": "pub",
      "fields": [],
      "derives": [
        "Debug",
        "PartialEq",
        "Hash",
        "Serialize",
        "Clone",
        "Eq",
        "Debug",
        "Deserialize",
        "Hash",
        "Serialize",
        "Error",
        "Eq",
        "PartialEq",
        "Debug",
        "Clone",
        "Serialize",
        "Hash",
        "PartialEq",
        "Eq",
        "Debug",
        "Clone",
        "Serialize",
        "Hash",
        "PartialEq",
        "Eq"
      ],
      "line": 98
    },
    {
      "name": "LengthId",
      "visibility": "pub(crate)",
      "fields": [],
      "derives": [
        "Debug",
        "PartialEq",
        "Hash",
        "Serialize",
        "Clone",
        "Eq",
        "Debug",
        "Deserialize",
        "Hash",
        "Serialize",
        "Error",
        "Eq",
        "PartialEq",
        "Debug",
        "Clone",
        "Serialize",
        "Hash",
        "PartialEq",
        "Eq",
        "Debug",
        "Clone",
        "Serialize",
        "Hash",
        "PartialEq",
        "Eq",
        "Debug",
        "Clone",
        "Serialize",
        "Hash",
        "Deserialize",
        "PartialEq",
        "Eq"
      ],
      "line": 192
    },
    {
      "name": "NonceSequence",
      "visibility": "",
      "fields": [],
      "derives": [
        "Clone",
        "Debug"
      ],
      "line": 18
    },
    {
      "name": "NoAlgorithm",
      "visibility": "pub",
      "fields": [],
      "derives": [
        "Clone",
        "Debug",
        "Debug"
      ],
      "line": 114
    },
    {
      "name": "HmacSha1",
      "visibility": "pub",
      "fields": [],
      "derives": [
        "Clone",
        "Debug",
        "Debug",
        "Debug"
      ],
      "line": 159
    },
    {
      "name": "HmacSha256",
      "visibility": "pub",
      "fields": [],
      "derives": [
        "Clone",
        "Debug",
        "Debug",
        "Debug",
        "Debug"
      ],
      "line": 187
    },
    {
      "name": "HmacSha512",
      "visibility": "pub",
      "fields": [],
      "derives": [
        "Clone",
        "Debug",
        "Debug",
        "Debug",
        "Debug",
        "Debug"
      ],
      "line": 215
    },
    {
      "name": "Blake3",
      "visibility": "pub",
      "fields": [],
      "derives": [
        "Clone",
        "Debug",
        "Debug",
        "Debug",
        "Debug",
        "Debug",
        "Debug"
      ],
      "line": 243
    },
    {
      "name": "GcmAes256",
      "visibility": "pub",
      "fields": [],
      "derives": [
        "Clone",
        "Debug",
        "Debug",
        "Debug",
        "Debug",
        "Debug",
        "Debug",
        "Debug"
      ],
      "line": 279
    },
    {
      "name": "Ed25519",
      "visibility": "pub",
      "fields": [],
      "derives": [
        "Clone",
        "Debug",
        "Debug",
        "Debug",
        "Debug",
        "Debug",
        "Debug",
        "Debug",
        "Debug"
      ],
      "line": 335
    },
    {
      "name": "Sha512",
      "visibility": "pub",
      "fields": [],
      "derives": [
        "Clone",
        "Debug",
        "Debug",
        "Debug",
        "Debug",
        "Debug",
        "Debug",
        "Debug",
        "Debug",
        "Debug"
      ],
      "line": 413
    },
    {
      "name": "Sha256",
      "visibility": "pub",
      "fields": [],
      "derives": [
        "Clone",
        "Debug",
        "Debug",
        "Debug",
        "Debug",
        "Debug",
        "Debug",
        "Debug",
        "Debug",
        "Debug",
        "Debug"
      ],
      "line": 417
    },
    {
      "name": "Md5",
      "visibility": "pub",
      "fields": [],
      "derives": [
        "Clone",
        "Debug",
        "Debug",
        "Debug",
        "Debug",
        "Debug",
        "Debug",
        "Debug",
        "Debug",
        "Debug",
        "Debug",
        "Debug"
      ],
      "line": 451
    },
    {
      "name": "Encryptable",
      "visibility": "pub",
      "fields": [
        "inner",
        "encrypted"
      ],
      "derives": [
        "Clone",
        "Debug",
        "Debug",
        "Debug",
        "Debug",
        "Debug",
        "Debug",
        "Debug",
        "Debug",
        "Debug",
        "Debug",
        "Debug",
        "Debug",
        "Clone"
      ],
      "line": 518
    },
    {
      "name": "TripleDesEde3CBC",
      "visibility": "pub",
      "fields": [
        "padding",
        "iv"
      ],
      "derives": [
        "Clone",
        "Debug",
        "Debug",
        "Debug",
        "Debug",
        "Debug",
        "Debug",
        "Debug",
        "Debug",
        "Debug",
        "Debug",
        "Debug",
        "Debug",
        "Clone"
      ],
      "line": 628
    },
    {
      "name": "RsaOaepSha256",
      "visibility": "pub",
      "fields": [],
      "derives": [
        "Clone",
        "Debug",
        "Debug",
        "Debug",
        "Debug",
        "Debug",
        "Debug",
        "Debug",
        "Debug",
        "Debug",
        "Debug",
        "Debug",
        "Debug",
        "Clone",
        "Debug"
      ],
      "line": 688
    },
    {
      "name": "EventPublisher",
      "visibility": "pub",
      "fields": [
        "writer",
        "config"
      ],
      "derives": [
        "Clone"
      ],
      "line": 21
    },
    {
      "name": "GlobalPaymentMethodId",
      "visibility": "pub",
      "fields": [],
      "derives": [
        "Debug",
        "Clone",
        "Hash",
        "PartialEq",
        "Eq",
        "serde::Serialize",
        "serde::Deserialize"
      ],
      "line": 11
    },
    {
      "name": "GlobalPaymentMethodSessionId",
      "visibility": "pub",
      "fields": [],
      "derives": [
        "Debug",
        "Clone",
        "Hash",
        "PartialEq",
        "Eq",
        "serde::Serialize",
        "serde::Deserialize",
        "Debug",
        "Clone",
        "Hash",
        "PartialEq",
        "Eq",
        "serde::Serialize",
        "serde::Deserialize"
      ],
      "line": 16
    },
    {
      "name": "GlobalRefundId",
      "visibility": "pub",
      "fields": [],
      "derives": [
        "Debug",
        "Clone",
        "Hash",
        "PartialEq",
        "Eq",
        "serde::Serialize",
        "serde::Deserialize"
      ],
      "line": 8
    }
  ],
  "enums": [
    {
      "name": "RequestError",
      "visibility": "pub",
      "variants": [
        "MultipartRenderingFailed",
        "MultipartReadFailed"
      ],
      "derives": [
        "Debug",
        "thiserror::Error"
      ],
      "line": 8
    },
    {
      "name": "Method",
      "visibility": "pub",
      "variants": [
        "Get",
        "Post",
        "Put",
        "Delete",
        "Patch"
      ],
      "derives": [
        "Debug",
        "thiserror::Error",
        "Clone",
        "Copy",
        "Debug",
        "Eq",
        "PartialEq",
        "Deserialize",
        "Serialize",
        "strum::Display",
        "strum::EnumString",
        "ToSchema"
      ],
      "line": 29
    },
    {
      "name": "ContentType",
      "visibility": "pub",
      "variants": [
        "Json",
        "FormUrlEncoded",
        "FormData",
        "Xml"
      ],
      "derives": [
        "Debug",
        "thiserror::Error",
        "Clone",
        "Copy",
        "Debug",
        "Eq",
        "PartialEq",
        "Deserialize",
        "Serialize",
        "strum::Display",
        "strum::EnumString",
        "ToSchema",
        "Deserialize",
        "Serialize",
        "Debug"
      ],
      "line": 38
    },
    {
      "name": "RequestContent",
      "visibility": "pub",
      "variants": [
        "Json",
        "FormUrlEncoded",
        "FormData",
        "Xml",
        "RawBytes"
      ],
      "derives": [
        "Debug",
        "thiserror::Error",
        "Clone",
        "Copy",
        "Debug",
        "Eq",
        "PartialEq",
        "Deserialize",
        "Serialize",
        "strum::Display",
        "strum::EnumString",
        "ToSchema",
        "Deserialize",
        "Serialize",
        "Debug",
        "Debug",
        "Serialize"
      ],
      "line": 74
    },
    {
      "name": "FormDataPart",
      "visibility": "pub",
      "variants": [
        "Text",
        "File"
      ],
      "derives": [
        "Debug",
        "thiserror::Error",
        "Clone",
        "Copy",
        "Debug",
        "Eq",
        "PartialEq",
        "Deserialize",
        "Serialize",
        "strum::Display",
        "strum::EnumString",
        "ToSchema",
        "Deserialize",
        "Serialize",
        "Debug",
        "Debug",
        "Serialize",
        "Debug",
        "Clone",
        "Serialize",
        "Debug",
        "Clone",
        "Serialize"
      ],
      "line": 88
    },
    {
      "name": "Env",
      "visibility": "pub",
      "variants": [
        "Development",
        "Production",
        "Sandbox"
      ],
      "derives": [
        "Debug",
        "Clone",
        "Copy",
        "PartialEq",
        "Eq",
        "Deserialize",
        "Serialize",
        "config_patch_derive::Patch"
      ],
      "line": 204
    },
    {
      "name": "ApiEventsType",
      "visibility": "pub",
      "variants": [
        "Payout",
        "Payment",
        "Refund",
        "PaymentMethod",
        "PaymentMethodCreate",
        "Customer",
        "BusinessProfile",
        "ApiKey",
        "User",
        "PaymentMethodList",
        "PaymentMethodListForPaymentMethods",
        "Webhooks",
        "Routing",
        "ResourceListAPI",
        "PaymentRedirectionResponse",
        "Gsm",
        "Miscellaneous",
        "Keymanager",
        "RustLocker",
        "ApplePayCertificatesMigration",
        "FraudCheck",
        "Recon",
        "ExternalServiceAuth",
        "Dispute",
        "Events",
        "PaymentMethodCollectLink",
        "Poll",
        "Analytics",
        "ClientSecret",
        "PaymentMethodSession",
        "Token",
        "ProcessTracker",
        "ProfileAcquirer",
        "ThreeDsDecisionRule"
      ],
      "derives": [
        "Debug",
        "Clone",
        "Serialize",
        "Clone",
        "Debug",
        "Eq",
        "PartialEq",
        "Serialize"
      ],
      "line": 54
    },
    {
      "name": "FlowName",
      "visibility": "pub",
      "variants": [
        "Authorize",
        "Refund",
        "Capture",
        "Void",
        "VoidPostCapture",
        "Psync",
        "Rsync",
        "AcceptDispute",
        "SubmitEvidence",
        "DefendDispute",
        "Dsync",
        "IncomingWebhook",
        "VerifyRedirectResponse",
        "SetupMandate",
        "RepeatPayment",
        "CreateOrder",
        "CreateSessionToken",
        "CreateAccessToken",
        "CreateConnectorCustomer",
        "PaymentMethodToken",
        "PreAuthenticate",
        "Authenticate",
        "PostAuthenticate",
        "SdkSessionToken",
        "MandateRevoke",
        "Unknown",
        "IncrementalAuthorization",
        "PayoutCreate",
        "PayoutTransfer",
        "PayoutGet",
        "PayoutVoid",
        "PayoutStage",
        "PayoutCreateLink",
        "PayoutCreateRecipient",
        "PayoutEnrollDisburseAccount"
      ],
      "derives": [
        "Debug",
        "Clone",
        "Serialize",
        "Clone",
        "Debug",
        "Eq",
        "PartialEq",
        "Serialize",
        "Debug",
        "Clone",
        "Serialize",
        "strum::Display",
        "Debug",
        "Clone",
        "Copy",
        "PartialEq",
        "Eq",
        "Serialize",
        "Deserialize"
      ],
      "line": 297
    },
    {
      "name": "EventStage",
      "visibility": "pub",
      "variants": [
        "ConnectorCall",
        "GrpcRequest"
      ],
      "derives": [
        "Debug",
        "Clone",
        "Serialize",
        "Clone",
        "Debug",
        "Eq",
        "PartialEq",
        "Serialize",
        "Debug",
        "Clone",
        "Serialize",
        "strum::Display",
        "Debug",
        "Clone",
        "Copy",
        "PartialEq",
        "Eq",
        "Serialize",
        "Deserialize",
        "Debug",
        "Clone",
        "Serialize",
        "Deserialize"
      ],
      "line": 378
    },
    {
      "name": "DateFormat",
      "visibility": "pub",
      "variants": [
        "YYYYMMDDHHmmss",
        "YYYYMMDD",
        "YYYYMMDDHHmm",
        "DDMMYYYYHHmmss"
      ],
      "derives": [
        "Debug"
      ],
      "line": 80
    },
    {
      "name": "GlobalEntity",
      "visibility": "pub(crate)",
      "variants": [
        "Customer",
        "Payment",
        "Attempt",
        "PaymentMethod",
        "Refund",
        "PaymentMethodSession",
        "Token"
      ],
      "derives": [
        "Debug",
        "Clone",
        "Hash",
        "PartialEq",
        "Eq",
        "serde::Serialize",
        "Clone",
        "Copy"
      ],
      "line": 24
    },
    {
      "name": "CellIdError",
      "visibility": "pub",
      "variants": [
        "InvalidCellLength",
        "InvalidCellIdFormat"
      ],
      "derives": [
        "Debug",
        "Clone",
        "Hash",
        "PartialEq",
        "Eq",
        "serde::Serialize",
        "Clone",
        "Copy",
        "Debug",
        "Clone",
        "Hash",
        "PartialEq",
        "Eq",
        "Debug",
        "Error",
        "PartialEq",
        "Eq"
      ],
      "line": 63
    },
    {
      "name": "GlobalIdError",
      "visibility": "pub(crate)",
      "variants": [
        "InvalidIdFormat",
        "LengthIdError",
        "CellIdError"
      ],
      "derives": [
        "Debug",
        "Clone",
        "Hash",
        "PartialEq",
        "Eq",
        "serde::Serialize",
        "Clone",
        "Copy",
        "Debug",
        "Clone",
        "Hash",
        "PartialEq",
        "Eq",
        "Debug",
        "Error",
        "PartialEq",
        "Eq",
        "Debug",
        "Error",
        "PartialEq",
        "Eq"
      ],
      "line": 121
    },
    {
      "name": "SuperpositionConfigError",
      "visibility": "pub",
      "variants": [
        "FileReadError",
        "ParseError",
        "ResolutionError"
      ],
      "derives": [
        "Debug",
        "thiserror::Error"
      ],
      "line": 19
    },
    {
      "name": "EmailStrategy",
      "visibility": "pub",
      "variants": [],
      "derives": [
        "Debug",
        "Copy",
        "Clone",
        "Deserialize"
      ],
      "line": 19
    },
    {
      "name": "IpAddress",
      "visibility": "pub",
      "variants": [],
      "derives": [
        "Debug",
        "Copy",
        "Clone",
        "Deserialize",
        "serde::Serialize",
        "serde::Deserialize",
        "Debug",
        "Clone",
        "PartialEq",
        "Eq",
        "Default",
        "Debug"
      ],
      "line": 88
    },
    {
      "name": "UpiVpaMaskingStrategy",
      "visibility": "pub",
      "variants": [],
      "derives": [
        "Debug",
        "Copy",
        "Clone",
        "Deserialize",
        "serde::Serialize",
        "serde::Deserialize",
        "Debug",
        "Clone",
        "PartialEq",
        "Eq",
        "Default",
        "Debug",
        "Debug"
      ],
      "line": 118
    },
    {
      "name": "EncryptionStrategy",
      "visibility": "pub",
      "variants": [],
      "derives": [
        "Debug",
        "Copy",
        "Clone",
        "Deserialize",
        "serde::Serialize",
        "serde::Deserialize",
        "Debug",
        "Clone",
        "PartialEq",
        "Eq",
        "Default",
        "Debug",
        "Debug",
        "Debug"
      ],
      "line": 136
    },
    {
      "name": "ParsingError",
      "visibility": "pub",
      "variants": [
        "EnumParseFailure",
        "StructParseFailure",
        "EncodeError",
        "UnknownError",
        "DateTimeParsingError",
        "EmailParsingError",
        "PhoneNumberParsingError",
        "FloatToDecimalConversionFailure",
        "DecimalToI64ConversionFailure",
        "StringToFloatConversionFailure",
        "I64ToDecimalConversionFailure",
        "StringToDecimalConversionFailure",
        "IntegerOverflow"
      ],
      "derives": [
        "Debug",
        "thiserror::Error"
      ],
      "line": 15
    },
    {
      "name": "ValidationError",
      "visibility": "pub",
      "variants": [
        "MissingRequiredField",
        "IncorrectValueProvided",
        "InvalidValue"
      ],
      "derives": [
        "Debug",
        "thiserror::Error",
        "Debug",
        "thiserror::Error",
        "Clone",
        "PartialEq"
      ],
      "line": 60
    },
    {
      "name": "PercentageError",
      "visibility": "pub",
      "variants": [
        "InvalidPercentageValue",
        "UnableToApplyPercentage"
      ],
      "derives": [
        "Debug",
        "thiserror::Error",
        "Debug",
        "thiserror::Error",
        "Clone",
        "PartialEq",
        "Debug",
        "Clone",
        "thiserror::Error",
        "PartialEq"
      ],
      "line": 76
    },
    {
      "name": "CryptoError",
      "visibility": "pub",
      "variants": [
        "EncodingFailed",
        "DecodingFailed",
        "MessageSigningFailed",
        "SignatureVerificationFailed",
        "InvalidKeyLength",
        "InvalidIvLength"
      ],
      "derives": [
        "Debug",
        "thiserror::Error",
        "Debug",
        "thiserror::Error",
        "Clone",
        "PartialEq",
        "Debug",
        "Clone",
        "thiserror::Error",
        "PartialEq",
        "Debug",
        "thiserror::Error"
      ],
      "line": 141
    },
    {
      "name": "EventPublisherError",
      "visibility": "pub",
      "variants": [
        "KafkaWriterInitializationFailed",
        "EventSerializationFailed",
        "EventPublishFailed",
        "InvalidConfiguration",
        "AlreadyInitialized",
        "EventProcessingFailed",
        "InvalidPath"
      ],
      "derives": [
        "Debug",
        "thiserror::Error",
        "Debug",
        "thiserror::Error",
        "Clone",
        "PartialEq",
        "Debug",
        "Clone",
        "thiserror::Error",
        "PartialEq",
        "Debug",
        "thiserror::Error",
        "Debug",
        "Clone",
        "PartialEq",
        "Default",
        "Debug",
        "thiserror::Error"
      ],
      "line": 183
    },
    {
      "name": "LineageParseError",
      "visibility": "pub",
      "variants": [
        "InvalidFormat",
        "UrlDecoding"
      ],
      "derives": [
        "Debug",
        "Clone",
        "PartialEq",
        "Eq",
        "Default",
        "Debug",
        "thiserror::Error"
      ],
      "line": 65
    },
    {
      "name": "LengthIdError",
      "visibility": "pub",
      "variants": [
        "MaxLengthViolated",
        "MinLengthViolated",
        "AlphanumericIdError"
      ],
      "derives": [
        "Debug",
        "PartialEq",
        "Hash",
        "Serialize",
        "Clone",
        "Eq",
        "Debug",
        "Deserialize",
        "Hash",
        "Serialize",
        "Error",
        "Eq",
        "PartialEq",
        "Debug",
        "Clone",
        "Serialize",
        "Hash",
        "PartialEq",
        "Eq",
        "Debug",
        "Clone",
        "Serialize",
        "Hash",
        "PartialEq",
        "Eq",
        "Debug",
        "Clone",
        "Serialize",
        "Hash",
        "Deserialize",
        "PartialEq",
        "Eq",
        "Debug",
        "Error",
        "PartialEq",
        "Eq"
      ],
      "line": 248
    },
    {
      "name": "GlobalPaymentMethodIdError",
      "visibility": "pub",
      "variants": [
        "ConstructionError"
      ],
      "derives": [
        "Debug",
        "Clone",
        "Hash",
        "PartialEq",
        "Eq",
        "serde::Serialize",
        "serde::Deserialize",
        "Debug",
        "Clone",
        "Hash",
        "PartialEq",
        "Eq",
        "serde::Serialize",
        "serde::Deserialize",
        "Debug",
        "thiserror::Error",
        "Clone",
        "PartialEq",
        "Eq"
      ],
      "line": 19
    },
    {
      "name": "GlobalPaymentMethodSessionIdError",
      "visibility": "pub",
      "variants": [
        "ConstructionError"
      ],
      "derives": [
        "Debug",
        "Clone",
        "Hash",
        "PartialEq",
        "Eq",
        "serde::Serialize",
        "serde::Deserialize",
        "Debug",
        "Clone",
        "Hash",
        "PartialEq",
        "Eq",
        "serde::Serialize",
        "serde::Deserialize",
        "Debug",
        "thiserror::Error",
        "Clone",
        "PartialEq",
        "Eq",
        "Debug",
        "thiserror::Error",
        "Clone",
        "PartialEq",
        "Eq"
      ],
      "line": 25
    }
  ],
  "traits": [
    {
      "name": "Encode",
      "visibility": "pub",
      "methods": [
        "convert_and_encode",
        "convert_and_url_encode",
        "url_encode",
        "encode_to_string_of_json",
        "encode_to_string_of_xml",
        "encode_to_value",
        "encode_to_vec"
      ],
      "line": 16
    },
    {
      "name": "BytesExt",
      "visibility": "pub",
      "methods": [
        "parse_struct"
      ],
      "line": 148
    },
    {
      "name": "ByteSliceExt",
      "visibility": "pub",
      "methods": [
        "parse_struct"
      ],
      "line": 178
    },
    {
      "name": "ConfigExt",
      "visibility": "pub",
      "methods": [
        "is_default",
        "is_empty_after_trim",
        "is_default_or_empty"
      ],
      "line": 205
    },
    {
      "name": "XmlExt",
      "visibility": "pub",
      "methods": [
        "parse_xml"
      ],
      "line": 265
    },
    {
      "name": "ValueExt",
      "visibility": "pub",
      "methods": [
        "parse_value"
      ],
      "line": 296
    },
    {
      "name": "AsyncExt",
      "visibility": "pub",
      "methods": [
        "async_map",
        "async_and_then",
        "async_unwrap_or_else"
      ],
      "line": 333
    },
    {
      "name": "OptionExt",
      "visibility": "pub",
      "methods": [
        "check_value_present",
        "get_required_value",
        "parse_enum",
        "parse_value",
        "update_value"
      ],
      "line": 432
    },
    {
      "name": "StringExt",
      "visibility": "pub",
      "methods": [
        "parse_enum",
        "parse_struct"
      ],
      "line": 531
    },
    {
      "name": "Patch",
      "visibility": "pub",
      "methods": [
        "apply"
      ],
      "line": 17
    },
    {
      "name": "AmountConvertor",
      "visibility": "pub",
      "methods": [
        "convert",
        "convert_back"
      ],
      "line": 25
    },
    {
      "name": "ApiEventMetric",
      "visibility": "pub",
      "methods": [
        "get_api_event_type"
      ],
      "line": 148
    },
    {
      "name": "TimeStrategy",
      "visibility": "pub",
      "methods": [
        "fmt"
      ],
      "line": 174
    },
    {
      "name": "Applicative",
      "visibility": "pub",
      "methods": [
        "pure"
      ],
      "line": 7
    },
    {
      "name": "ErrorSwitch",
      "visibility": "pub",
      "methods": [
        "switch"
      ],
      "line": 92
    },
    {
      "name": "ErrorSwitchFrom",
      "visibility": "pub",
      "methods": [
        "switch_from"
      ],
      "line": 100
    },
    {
      "name": "ReportSwitchExt",
      "visibility": "pub",
      "methods": [
        "switch"
      ],
      "line": 117
    },
    {
      "name": "GenerateId",
      "visibility": "pub",
      "methods": [
        "generate"
      ],
      "line": 301
    },
    {
      "name": "SignMessage",
      "visibility": "pub",
      "methods": [
        "sign_message"
      ],
      "line": 70
    },
    {
      "name": "VerifySignature",
      "visibility": "pub",
      "methods": [
        "verify_signature"
      ],
      "line": 80
    },
    {
      "name": "EncodeMessage",
      "visibility": "pub",
      "methods": [
        "encode_message"
      ],
      "line": 92
    },
    {
      "name": "DecodeMessage",
      "visibility": "pub",
      "methods": [
        "decode_message"
      ],
      "line": 102
    },
    {
      "name": "GenerateDigest",
      "visibility": "pub",
      "methods": [
        "generate_digest"
      ],
      "line": 420
    }
  ]
}